APB_slave.v
module APB_slave(input PCLK,               //clock
                 input PRESETn,            //active low reset
                 input [4:0] PADDR,        //32 bit address
                 input PSELx,              //select slave
                 input PENABLE,            //indicate 2nd or subsequent cycle
                 input PWRITE,             //high->write, low->read
                 input [31:0]PWDATA,       //32 bit Data Bus
                 output reg PREADY,        //ready status by slave
                 output reg [31:0] PRDATA, //32 bit Data Bus
                 output reg PSLVERR = 0);  //Error occurred
    
    reg [31:0] mem [0:31]; //32 bit wide and 32 locations
    
    reg [31:0] temp_data;
    
    always @(*) begin
        if (!PRESETn)
        begin
            PREADY  = 0;
            PSLVERR = 0;
        end
        else
        begin
            if (PSELx && !PENABLE && !PWRITE) begin  //setup stage READ
                PREADY = 0;
            end
            else if (PSELx && PENABLE && !PWRITE) begin  //access stage READ
                PREADY = 1;
                PRDATA = mem[PADDR];
            end
            else if (PSELx && !PENABLE && PWRITE) begin  //setup stage write
                PREADY = 0;
            end
            else if (PSELx && PENABLE && PWRITE) begin  //access stage write
                PREADY     = 1;
                mem[PADDR] = PWDATA;
            end
            else
                PREADY = 0;
        end
    end
    
    
endmodule

APB_master.v
module APB_master(input Transfer,              //temp signals for master input
                  input Wr_Rd,                 //temp signals for master input
                  input [4:0] Address,         //temp signals for master input
                  input [31:0] write_data,     //temp signals for master input
                  output reg [31:0] read_data, //temp signals for master input
                  input PCLK,                  //clock
                  input PRESETn,               //active low async reset
                  input PREADY,                //input by slave
                  input [31:0] PRDATA,         //32 bit bus to read data
                  input PSLVERR,               //Error signal by slave
                  output reg [4:0] PADDR,      //32 bit address
                  output reg PSELx,            //select slave
                  output reg PENABLE,          //indicate 2nd or subsequent cycle
                  output reg PWRITE,           //high->write, low->read
                  output reg [31:0] PWDATA);   //32 bit bus to write data
    
    parameter IDLE = 2'b00, SETUP = 2'b01, ACCESS = 2'b10;
    reg [1:0] ps,ns;
    
    
    always @(posedge PCLK) begin
        if (!PRESETn)
            ps <= IDLE;
        else
            ps <= ns;
    end
    
    always @(ps,Transfer,PREADY) begin
        if (!PRESETn  || !Transfer)
            ns <= IDLE;
        else
        begin
            PWRITE = Wr_Rd;
            
            case (ps)
                
                IDLE:begin
                    PSELx   = 0;
                    PENABLE = 0;
                    ns <= SETUP;
                end
                
                SETUP:begin
                    PSELx   = 1;
                    PENABLE = 0;
                    PADDR   = Address;
                    
                    if (PWRITE)
                        PWDATA   <= write_data;
                    
                    if (!PSLVERR)
                        ns <= ACCESS;
                    else
                        ns <= IDLE;
                end
                
                ACCESS:begin
                    PSELx   = 1;
                    PENABLE = 1;
                    if (!PSLVERR)
                    begin
                        if (!PREADY) begin
                            if (PWRITE) begin
                                ns <= ACCESS;
                            end
                            else if (!PWRITE) begin
                                read_data = PRDATA;
                                ns <= ACCESS;
                            end
                        end
                        else if (PREADY)
                            ns <= SETUP;
                    end
                    else
                        ns <= IDLE;
                end
                        
                default: ns <= IDLE;
            endcase
        end
                    
    end
                
endmodule

APB_top.v
`include "APB_master.v"
`include "APB_slave.v"

module APB_top(input PCLK,
               input PRESETn,
               input Transfer,
               input Wr_Rd,
               input [4:0] Address,
               input [31:0] write_data,
               output [31:0] read_data);
    
    wire [4:0] PADDR;
    wire [31:0] PWDATA,PRDATA;
    wire PSELx,PENABLE,PWRITE,PREADY,PSLVERR;
    
    APB_master Design_master(Transfer,Wr_Rd,Address,write_data,read_data,PCLK,PRESETn,PREADY,PRDATA,PSLVERR,PADDR,PSELx,PENABLE,PWRITE,PWDATA);
    APB_slave Design_slave(PCLK,PRESETn,PADDR,PSELx,PENABLE,PWRITE,PWDATA,PREADY,PRDATA,PSLVERR);
    
endmodule

APB_tb.v
module APB_tb;
    reg PCLK, PRESETn, Transfer, Wr_Rd; 
    reg [4:0] Address; 
    reg [31:0] write_data; 
    wire [31:0] read_data; 
    APB_top DUT (PCLK,PRESETn,Transfer,Wr_Rd,Address,write_data,read_data);
    
    initial begin
        PCLK = 0;
        forever begin
            #5 PCLK = ~PCLK;
        end
    end
    
    
    initial begin
        PRESETn  = 1;
        Transfer = 1;
        
        //Write Operation 1
        Address = 5'b10010;
        #10
        Wr_Rd      = 1;
        write_data = 32'hDEADBEEF;
        #10
        
        //Write Operation 2
        Address    = 5'b10101;
        Wr_Rd      = 1;
        write_data = 32'hDABBCAFE;
        #30
        write_data = 32'hx;
        #10
        Transfer     = 0;
        #15 Transfer = 1;

        //Read Operation 1
        Wr_Rd   = 0;
        Address = 5'b10010;
        
        //Read Operation 2
        #30
        Address = 5'b10101;
        
        #20 Transfer = 0;
        #20 $finish;
        
    end
    
    
    initial begin
        $dumpfile("APB_wave.vcd");
        $dumpvars;
    end
    
endmodule

APB_wave.vcd
$date
	Thu Jul 21 08:49:08 2022
$end
$version
	Icarus Verilog
$end
$timescale
	1s
$end
$scope module APB_tb $end
$var wire 32 ! read_data [31:0] $end
$var reg 5 " Address [4:0] $end
$var reg 1 # PCLK $end
$var reg 1 $ PRESETn $end
$var reg 1 % Transfer $end
$var reg 1 & Wr_Rd $end
$var reg 32 ' write_data [31:0] $end
$scope module DUT $end
$var wire 5 ( Address [4:0] $end
$var wire 1 # PCLK $end
$var wire 1 $ PRESETn $end
$var wire 1 % Transfer $end
$var wire 1 & Wr_Rd $end
$var wire 32 ) write_data [31:0] $end
$var wire 32 * read_data [31:0] $end
$var wire 1 + PWRITE $end
$var wire 32 , PWDATA [31:0] $end
$var wire 1 - PSLVERR $end
$var wire 1 . PSELx $end
$var wire 1 / PREADY $end
$var wire 32 0 PRDATA [31:0] $end
$var wire 1 1 PENABLE $end
$var wire 5 2 PADDR [4:0] $end
$scope module Design_master $end
$var wire 5 3 Address [4:0] $end
$var wire 1 # PCLK $end
$var wire 1 $ PRESETn $end
$var wire 1 % Transfer $end
$var wire 1 & Wr_Rd $end
$var wire 32 4 write_data [31:0] $end
$var wire 1 - PSLVERR $end
$var wire 1 / PREADY $end
$var wire 32 5 PRDATA [31:0] $end
$var reg 5 6 PADDR [4:0] $end
$var reg 1 1 PENABLE $end
$var reg 1 . PSELx $end
$var reg 32 7 PWDATA [31:0] $end
$var reg 1 + PWRITE $end
$var reg 2 8 ns [1:0] $end
$var reg 2 9 ps [1:0] $end
$var reg 32 : read_data [31:0] $end
$upscope $end
$scope module Design_slave $end
$var wire 5 ; PADDR [4:0] $end
$var wire 1 # PCLK $end
$var wire 1 1 PENABLE $end
$var wire 1 $ PRESETn $end
$var wire 1 . PSELx $end
$var wire 32 < PWDATA [31:0] $end
$var wire 1 + PWRITE $end
$var reg 32 = PRDATA [31:0] $end
$var reg 1 / PREADY $end
$var reg 1 - PSLVERR $end
$upscope $end
$upscope $end
$upscope $end
$enddefinitions $end
#0
$dumpvars
bx =
bx <
bx ;
bx :
bx 9
b0 8
bx 7
bx 6
bx 5
bx 4
b10010 3
bx 2
x1
bx 0
0/
x.
0-
bx ,
x+
bx *
bx )
b10010 (
bx '
x&
1%
1$
0#
b10010 "
bx !
$end
#5
b1 8
01
0.
b0 9
1#
#10
0#
b11011110101011011011111011101111 '
b11011110101011011011111011101111 )
b11011110101011011011111011101111 4
1&
#15
b10 8
b11011110101011011011111011101111 ,
b11011110101011011011111011101111 7
b11011110101011011011111011101111 <
b10010 2
b10010 6
b10010 ;
1.
1+
b1 9
1#
#20
0#
b11011010101110111100101011111110 '
b11011010101110111100101011111110 )
b11011010101110111100101011111110 4
b10101 "
b10101 (
b10101 3
#25
b1 8
1/
11
b10 9
1#
#30
0#
#35
b10 8
b11011010101110111100101011111110 ,
b11011010101110111100101011111110 7
b11011010101110111100101011111110 <
0/
b10101 2
b10101 6
b10101 ;
01
b1 9
1#
#40
0#
#45
b1 8
1/
11
b10 9
1#
#50
0#
bx '
bx )
bx 4
#55
b10 8
bx ,
bx 7
bx <
0/
01
b1 9
1#
#60
b0 8
0#
0%
#65
b0 9
1#
#70
0#
#75
b1 8
0.
0+
1#
b10010 "
b10010 (
b10010 3
0&
1%
#80
0#
#85
b10 8
b10010 2
b10010 6
b10010 ;
1.
b1 9
1#
#90
0#
#95
b1 8
b11011110101011011011111011101111 0
b11011110101011011011111011101111 5
b11011110101011011011111011101111 =
1/
11
b10 9
1#
#100
0#
#105
b10 8
0/
b10101 2
b10101 6
b10101 ;
01
b1 9
1#
b10101 "
b10101 (
b10101 3
#110
0#
#115
b1 8
b11011010101110111100101011111110 0
b11011010101110111100101011111110 5
b11011010101110111100101011111110 =
1/
b11011110101011011011111011101111 !
b11011110101011011011111011101111 *
b11011110101011011011111011101111 :
11
b10 9
1#
#120
0#
#125
b1 9
b0 8
1#
0%
#130
0#
#135
b0 9
1#
